{
  "generator-jhipster": {
    "baseName": "TestProject5",
    "packageName": "com.cg.TestProject5",
    "applicationType": "monolith",
    "authenticationType": "session",
    "hibernateCache": "ehcache",
    "devDatabaseType": "h2Disk",
    "prodDatabaseType": "mysql",
    "buildTool": "maven",
    "websocket": false,
    "clusteredHttpSession": "no",
    "searchEngine": false,
    "enableSocialSignIn": false,
    "useSass": true,
    "enableTranslation": false,
    "jhiPrefix": "cg",
    "databaseType": "sql",
    "serverPort": "8008",
    "packageFolder": "com/cg/TestProject5",
    "testFrameworks": ["gatling", "cucumber", "protractor"],
    "jhipsterVersion": "6.10.3",
    "cacheProvider": "ehcache",
    "messageBroker": false,
    "serviceDiscoveryType": false,
    "rememberMeKey": "086029581564f2ba043636a01a7cab581550f8c02620ffbb3f8c0067605412ddfaab2fffef2968a167b95f1eba8e67226257",
    "embeddableLaunchScript": false,
    "clientPackageManager": "npm",
    "clientFramework": "angularX",
    "clientTheme": "none",
    "creationTimestamp": 1610972435735,
    "entitySuffix": "",
    "dtoSuffix": "DTO",
    "otherModules": [],
    "blueprints": []
  }
}
